[
  {
    "id": 1,
    "name": "Primary School",
    "description": "Foundational assessments for young learners",
    "classes": "Standards 1-5",
    "ageRange": "6-11 years",
    "color": "bg-blue-500",
    "assessments": ["Verbal Reasoning", "Numerical Ability", "Attention & Memory"],
    "totalTests": 8,
    "sections": [
      {
        "id": 101,
        "name": "Verbal Reasoning",
        "description": "Word understanding and language skills",
        "questions": 25
      },
      {
        "id": 102,
        "name": "Numerical Ability",
        "description": "Basic math and number concepts",
        "questions": 20
      },
      {
        "id": 103,
        "name": "Attention & Memory",
        "description": "Focus and recall abilities",
        "questions": 15
      }
    ]
  },
  {
    "id": 2,
    "name": "Middle School",
    "description": "Comprehensive evaluations for developing minds",
    "color": "bg-green-500",
    "assessments": ["Logical Reasoning", "Personality Assessment", "Interest Exploration"],
    "totalTests": 12,
    "sections": [
      {
        "id": 201,
        "name": "Logical Reasoning",
        "description": "Problem-solving and analytical thinking",
        "questions": 30
      }
    ]
  },
  {
    "id": 3,
    "name": "Secondary School",
    "description": "Advanced assessments for career guidance",
    "color": "bg-purple-500",
    "assessments": ["Aptitude Testing", "Career Interests", "Learning Styles", "Advanced Personality"],
    "totalTests": 15,
    "sections": []
  }
]
